openestimctrl/__init__.py
openestimctrl/dglab/__init__.py
openestimctrl/dglab/dglabestim01.py
openestimctrl/yokonex/__init__.py
openestimctrl/yokonex/yokonexes01.py
openestimctrl-0.1.6.dist-info/LICENSE
openestimctrl-0.1.6.dist-info/METADATA
openestimctrl-0.1.6.dist-info/WHEEL
openestimctrl-0.1.6.dist-info/top_level.txt
openestimctrl-0.1.6.dist-info/RECORD
