Metadata-Version: 2.1
Name: openestimctrl
Version: 0.1.6
Summary: Python binding for OpenEStimCtrl
Home-page: https://github.com/OpenEStimCtrl/OpenEStimCtrl-Python
Author: Sound Reload
License: AGPL-3.0
Classifier: License :: OSI Approved :: MIT License
Classifier: Programming Language :: Python
Classifier: Programming Language :: Python :: 3
Classifier: Programming Language :: Python :: 3.6
Classifier: Programming Language :: Python :: Implementation :: CPython
Classifier: Programming Language :: Python :: Implementation :: PyPy
Requires-Python: >=3.6.0
License-File: LICENSE
Requires-Dist: cffi
